{
  "analysis_date": "2024-01-XX",
  "system_status": {
    "scraper_integration": "\u274c Not connected",
    "file_organization": "\u274c Needs restructuring",
    "import_management": "\u274c Needs updating",
    "user_flows": "\u2705 Mostly working",
    "overall_health": "80%"
  },
  "critical_issues": [
    "Recommendation system not connected to scraper data",
    "21 pages scattered in root directory",
    "52 lib files scattered in root directory",
    "Import paths will break after restructuring"
  ],
  "recommended_actions": [
    "1. Fix scraper integration (HIGH PRIORITY)",
    "2. Execute folder restructure (MEDIUM PRIORITY)",
    "3. Update import paths (LOW PRIORITY)",
    "4. Test all functionality"
  ],
  "files_analyzed": {
    "python_scripts": 5,
    "json_analysis_files": 5,
    "markdown_docs": 5,
    "total_files_checked": 228
  },
  "restructure_plan": {
    "pages_to_move": 21,
    "lib_files_to_move": 52,
    "imports_to_update": 303,
    "estimated_time": "8 minutes"
  }
}